Ypredict-0.0.3.data/scripts/snpfilter.py
Ypredict-0.0.3.data/scripts/ypredict.py
Ypredict-0.0.3.dist-info/METADATA
Ypredict-0.0.3.dist-info/RECORD
Ypredict-0.0.3.dist-info/WHEEL
Ypredict-0.0.3.dist-info/top_level.txt
bin/snpfilter.py
bin/ypredict.py
