Metadata-Version: 2.1
Name: Ypredict
Version: 0.0.3
Summary: a very fast Y-haplogroup caller
Home-page: https://github.com/N-damo/ypredict-master
Author: Li'an Lin
Author-email: 21620151153308@stu.xmu.edu.cn
License: GPL3
Keywords: Y haplogroup
Platform: UNKNOWN
Requires-Dist: biopython (>=1.72)
